{
  "main": {
    "id": "5324373015726ba8",
    "type": "split",
    "children": [
      {
        "id": "578943111367837d",
        "type": "split",
        "children": [
          {
            "id": "ffdd882f7f1de925",
            "type": "tabs",
            "children": [
              {
                "id": "9f3b60f67cdaa683",
                "type": "leaf",
                "state": {
                  "type": "markdown",
                  "state": {
                    "file": "202501251438 - afterdark design philosophy.md",
                    "mode": "source",
                    "backlinks": true,
                    "source": true
                  },
                  "icon": "lucide-file",
                  "title": "202501251438 - afterdark design philosophy"
                },
                "group": "878b2fe65e83c640"
              }
            ]
          },
          {
            "id": "1803dfe4a6e792ae",
            "type": "tabs",
            "children": [
              {
                "id": "d4128db919d75821",
                "type": "leaf",
                "state": {
                  "type": "markdown",
                  "state": {
                    "file": "202501251438 - afterdark design philosophy.md",
                    "mode": "preview",
                    "backlinks": true,
                    "source": true
                  },
                  "icon": "lucide-file",
                  "title": "202501251438 - afterdark design philosophy"
                },
                "group": "878b2fe65e83c640"
              }
            ]
          }
        ],
        "direction": "horizontal"
      }
    ],
    "direction": "vertical"
  },
  "left": {
    "id": "1fa23c93fef3f121",
    "type": "split",
    "children": [
      {
        "id": "7beeaac5abdef103",
        "type": "tabs",
        "dimension": 69.60621186910704,
        "children": [
          {
            "id": "5d4669a5803d0c8d",
            "type": "leaf",
            "state": {
              "type": "file-explorer",
              "state": {
                "sortOrder": "alphabetical"
              },
              "icon": "lucide-folder-closed",
              "title": "Files"
            }
          },
          {
            "id": "dd2d26c4be240688",
            "type": "leaf",
            "state": {
              "type": "search",
              "state": {
                "query": "",
                "matchingCase": false,
                "explainSearch": false,
                "collapseAll": false,
                "extraContext": false,
                "sortOrder": "alphabetical"
              },
              "icon": "lucide-search",
              "title": "Search"
            }
          },
          {
            "id": "769296cb993d83f9",
            "type": "leaf",
            "state": {
              "type": "bookmarks",
              "state": {},
              "icon": "lucide-bookmark",
              "title": "Bookmarks"
            }
          }
        ]
      },
      {
        "id": "136ecc4ac9dd7174",
        "type": "tabs",
        "dimension": 30.393788130892958,
        "children": [
          {
            "id": "c34f2749b4bc71da",
            "type": "leaf",
            "pinned": true,
            "state": {
              "type": "graph",
              "state": {},
              "pinned": true,
              "icon": "lucide-git-fork",
              "title": "Graph view"
            }
          }
        ]
      }
    ],
    "direction": "horizontal",
    "width": 474.5
  },
  "right": {
    "id": "6eb15b0e5d98e2dd",
    "type": "split",
    "children": [
      {
        "id": "f97704eb5c85dfc2",
        "type": "tabs",
        "children": [
          {
            "id": "5573a2084cb7d1a1",
            "type": "leaf",
            "state": {
              "type": "backlink",
              "state": {
                "file": "05 - Archives/202501240915 - Number.md",
                "collapseAll": false,
                "extraContext": false,
                "sortOrder": "alphabetical",
                "showSearch": false,
                "searchQuery": "",
                "backlinkCollapsed": false,
                "unlinkedCollapsed": true
              },
              "icon": "links-coming-in",
              "title": "Backlinks for 202501240915 - Number"
            }
          },
          {
            "id": "afd6f86187bc6374",
            "type": "leaf",
            "state": {
              "type": "outgoing-link",
              "state": {
                "file": "05 - Archives/202501240915 - Number.md",
                "linksCollapsed": false,
                "unlinkedCollapsed": true
              },
              "icon": "links-going-out",
              "title": "Outgoing links from 202501240915 - Number"
            }
          },
          {
            "id": "246ac985f5e50aef",
            "type": "leaf",
            "state": {
              "type": "tag",
              "state": {
                "sortOrder": "frequency",
                "useHierarchy": true
              },
              "icon": "lucide-tags",
              "title": "Tags"
            }
          },
          {
            "id": "805f9d3f0a0e0745",
            "type": "leaf",
            "state": {
              "type": "outline",
              "state": {
                "file": "Welcome.md"
              },
              "icon": "lucide-list",
              "title": "Outline of Welcome"
            }
          },
          {
            "id": "021c24cfdec7accd",
            "type": "leaf",
            "state": {
              "type": "all-properties",
              "state": {
                "sortOrder": "frequency",
                "showSearch": false,
                "searchQuery": ""
              },
              "icon": "lucide-archive",
              "title": "All properties"
            }
          },
          {
            "id": "08b9f54174cf03fb",
            "type": "leaf",
            "state": {
              "type": "git-view",
              "state": {},
              "icon": "git-pull-request",
              "title": "Source Control"
            }
          },
          {
            "id": "94c3b2b9e18125f3",
            "type": "leaf",
            "state": {
              "type": "empty",
              "state": {},
              "icon": "lucide-file",
              "title": "New tab"
            }
          },
          {
            "id": "8c1c6d28123d90e9",
            "type": "leaf",
            "state": {
              "type": "chat-view",
              "state": {
                "file": "Chats/New Chat.md"
              },
              "icon": "message-square",
              "title": "New Chat"
            }
          }
        ],
        "currentTab": 5
      }
    ],
    "direction": "horizontal",
    "width": 614.5
  },
  "left-ribbon": {
    "hiddenItems": {
      "zk-prefixer:Create new unique note": false,
      "graph:Open graph view": false,
      "switcher:Open quick switcher": false,
      "canvas:Create new canvas": false,
      "daily-notes:Open today's daily note": false,
      "templates:Insert template": false,
      "command-palette:Open command palette": false,
      "obsidian-excalidraw-plugin:Create new drawing": false,
      "templater-obsidian:Templater": false,
      "omnisearch:Omnisearch": false,
      "open-vscode:VSCode": false,
      "obsidian-git:Open Git source control": false,
      "smart-second-brain:Open S2B Chat": false
    }
  },
  "active": "5d4669a5803d0c8d",
  "lastOpenFiles": [
    "01 - Areas/02 - Physics/00 - Motion, Forces and Energy/202501220000 - Mass and weight.md",
    "202501251438 - afterdark design philosophy.md",
    "00 - Projects/01 - afterdark/Untitled.md",
    "01 - Areas/02 - Physics/00 - Motion, Forces and Energy/202501220000 - Density.md",
    "05 - Archives/202501240915 - Number.md",
    "Chats/New Chat.md",
    "05 - Archives/202501241723 - Physics questions.md",
    "04 - Bites/states of matter.md",
    "Chats",
    "01 - Areas/02 - Physics/01 - Thermal physics/202501220000 - Kinetic particle model of matter.md",
    "05 - Archives/202501230914 - Kinetic particle model of matter.md",
    "99 - Meta/Attachments/202501240915 - Number-20250124095031563.webp",
    "99 - Meta/Attachments/202501240915 - Number-20250124093951306.webp",
    "99 - Meta/Attachments/202501240915 - Number-20250124093724018.webp",
    "99 - Meta/Attachments/Pasted image 20250124092844.png",
    "99 - Meta/Attachments/202501240915 - Number-20250124092401781.webp",
    "02 - Resources/202501240904 - Newton's First Law - Newton's Laws - National 5 Physics Revision - BBC Bitesize.md",
    "01 - Areas/04 - Mathematics/00 - Number",
    "04 - Bites/00 - Formulas/gravitational field strength.md",
    "02 - Resources/2025-01-24T090400+0100 - Newton's First Law - Newton's Laws - National 5 Physics Revision - BBC Bitesize.md",
    "02 - Resources/2025-01-24T090133+0100 - Newton's First Law - Newton's Laws - National 5 Physics Revision - BBC Bitesize.md",
    "02 - Resources/Newton's First Law - Newton's Laws - National 5 Physics Revision - BBC Bitesize.md",
    "01 - Areas/02 - Physics/00 - Motion, Forces and Energy/202501220000 - Physical quantities and measurement techniques.md",
    "04 - Bites/00 - Formulas/Newton's laws of motion.md",
    "Clippings/Newton's First Law - Newton's Laws - National 5 Physics Revision - BBC Bitesize.md",
    "Clippings",
    "01 - Areas/02 - Physics/00 - Motion, Forces and Energy/202501220000 - Energy, work and power.md",
    "01 - Areas/02 - Physics/00 - Motion, Forces and Energy/202501220000 - Motion.md",
    "04 - Bites/acceleration.md",
    "04 - Bites/00 - Formulas/Boyle's law.md",
    "01 - Areas/01 - Chemistry/00 - States of matter/202501220000 - Solids, liquids and gases.md",
    "03 - Fleeting/202501232059 - How does desktop environments work on Linux.md",
    "01 - Areas/01 - Chemistry/05 - Chemical energetics/202501220000 - Exothermic and endothermic reactions.md",
    "00 - Projects/01 - afterdark/202501231559 - afterdark in comparison to Catppuccin.md",
    "00 - Projects/01 - afterdark",
    "99 - Meta/Attachments/Pasted image 20250123114259.png",
    "99 - Meta/Attachments/Pasted image 20250123115344.png",
    "99 - Meta/Attachments/202501230914 - Kinetic particle model of matter-20250123115958516.webp",
    "04 - Bites/00 - Formulas",
    "99 - Meta/Attachments/202501230914 - Kinetic particle model of matter-20250123113435604.webp",
    "99 - Meta/Attachments/202501230914 - Kinetic particle model of matter-20250123111315092.webp",
    "99 - Meta/Excalidraw",
    "Untitled.canvas",
    "Excalidraw",
    "02 - Resources/202501221301 - Classtask.pdf",
    "00 - Projects/00 - aoiweb",
    "01 - Areas/01 - Chemistry/Key Terms",
    "Academic/Physics/Motion, Forces and Energy/Untitled.canvas",
    "Untitled 1.canvas"
  ]
}